{
  "@type" : "alfa.rt.model.Record",
  "Doc" : "Fixed Price Leg of a Commodity Swap. It defines schedule of fixed payments associated with a commodity swap.",
  "Name" : {
    "@type" : "alfa.rt.model.UdtVersionedName",
    "FullyQualifiedName" : "FpML5.confirmation.FixedPriceLeg",
    "UdtType" : "recordType"
  },
  "Includes" : [ ],
  "Source" : {
    "@type" : "alfa.rt.model.Union__ModelBaseNode_Source",
    "Contents" : "/#\n   Fixed Price Leg of a Commodity Swap. It defines schedule of fixed payments associated with a commodity swap.\n #/\nrecord FpML5.confirmation.FixedPriceLeg {\n  # A reference to the party responsible for making the payments defined by this structure.\n  payerPartyReference : FpML5.confirmation.PartyReference\n\n  # A reference to the account responsible for making the payments defined by this structure.\n  payerAccountReference : FpML5.confirmation.AccountReference?\n\n  # A reference to the party that receives the payments corresponding to this structure.\n  receiverPartyReference : FpML5.confirmation.PartyReference\n\n  # A reference to the account that receives the payments corresponding to this structure.\n  receiverAccountReference : FpML5.confirmation.AccountReference?\n\n  # The Calculation Period dates for this leg of the trade where the Calculation Periods are all one day long. Only dates explicitly included determine the Calculation Periods and there is a Calculation Period for each date specified. As such one-day Calculation Period are typical a physically-settled emissions or metals trades it is expected that this element will not be used in performance swaps.\n  calculationDates : FpML5.confirmation.AdjustableDates\n\n  # The Calculation Period start dates for this leg of the swap. This type is only intended to be used if the Calculation Periods differ on each leg. If Calculation Periods mirror another leg, then the calculationPeriodsReference element should be used to point to the Calculation Periods on that leg - or the calculationPeriodsScheduleReference can be used to point to the Calculation Periods Schedule for that leg.\n  calculationPeriods : FpML5.confirmation.AdjustableDates\n\n  # The Calculation Periods for this leg of the swap. This type is only intended to be used if the Calculation Periods differ on each leg. If Calculation Periods mirror another leg, then the calculationPeriodsReference element should be used to point to the Calculation Periods on the other leg - or the calculationPeriodsScheduleReference can be used to point to the Calculation Periods Schedule for that leg.\n  calculationPeriodsSchedule : FpML5.confirmation.CommodityCalculationPeriodsSchedule\n\n  # A pointer style reference to the Calculation Periods defined on another leg.\n  calculationPeriodsReference : FpML5.confirmation.CalculationPeriodsReference\n\n  # A pointer style reference to the Calculation Periods Schedule defined on another leg.\n  calculationPeriodsScheduleReference : FpML5.confirmation.CalculationPeriodsScheduleReference\n\n  # A pointer style reference to single-day-duration Calculation Periods defined on another leg.\n  calculationPeriodsDatesReference : FpML5.confirmation.CalculationPeriodsDatesReference\n\n  # Allows the specification of a Fixed Price that varies over the life of the trade.\n  fixedPriceSchedule : FpML5.confirmation.CommodityFixedPriceSchedule\n\n  # Fixed price on which fixed payments are based.\n  fixedPrice : FpML5.confirmation.FixedPrice\n\n  # For a WET Voyager Charter Commodity Swap, the number of Worldscale Points for purposes of the calculation of a Fixed Amount.\n  worldscaleRate : decimal\n\n  # For a DRY Voyage Charter or Time Charter Commodity Swap, the price per relevant unit for pruposes of the calculation of a Fixed Amount.\n  contractRate : FpML5.confirmation.NonNegativeMoney\n\n  # For an electricity transaction, the fixed price for one or more groups of Settlement Periods on which fixed payments are based. If the fixed price differs for different groups of Settlement Periods, this element should be repeated.\n  settlementPeriodsPrice : FpML5.confirmation.SettlementPeriodsFixedPrice\n\n  # The total amount of all fixed payments due during the term of the trade.\n  totalPrice : FpML5.confirmation.NonNegativeMoney?\n\n  # Allows the documentation of a shaped notional trade where the notional changes over the life of the transaction.\n  notionalQuantitySchedule : FpML5.confirmation.CommodityNotionalQuantitySchedule\n\n  # The Notional Quantity.\n  notionalQuantity : FpML5.confirmation.CommodityNotionalQuantity\n\n  # For an electricity transaction, the Notional Quantity for a one or more groups of Settlement Periods to which the Notional Quantity is based. If the schedule differs for different groups of Settlement Periods, this element should be repeated.\n  settlementPeriodsNotionalQuantity : FpML5.confirmation.CommoditySettlementPeriodsNotionalQuantity\n\n  # The Total Notional Quantity.\n  totalNotionalQuantity : decimal?\n\n  # A pointer style reference to a quantity defined on another leg.\n  quantityReference : FpML5.confirmation.QuantityReference\n\n  # The Payment Dates of the trade relative to the Calculation Periods.\n  relativePaymentDates : FpML5.confirmation.CommodityRelativePaymentDates\n\n  # Dates on which payments will be made.\n  paymentDates : FpML5.confirmation.AdjustableDatesOrRelativeDateOffset\n\n  # If present and true indicates that the Payment Date(s) are specified in the relevant master agreement.\n  masterAgreementPaymentDates : boolean\n\n  # Whether the Flat Rate is the New Worldwide Tanker Nominal Freight Scale for the Freight Index Route taken at the Trade Date of the transaction or taken on each Pricing Date.\n  flatRate : string\n\n  # If flatRate is set to \"Fixed\", the actual value of the Flat Rate.\n  flatRateAmount : FpML5.confirmation.NonNegativeMoney?\n\n  id : string?\n\n}"
  },
  "AllFields" : {
    "payerPartyReference" : {
      "@type" : "alfa.rt.model.Field",
      "Doc" : "A reference to the party responsible for making the payments defined by this structure.",
      "Name" : "payerPartyReference",
      "DataType" : {
        "@type" : "alfa.rt.model.UdtDataType",
        "FullyQualifiedName" : "FpML5.confirmation.PartyReference",
        "UdtType" : "recordType"
      },
      "DeclTypeDefDataType" : {
        "@type" : "alfa.rt.model.TypeDefDataType",
        "TypeName" : "FpML5.confirmation.PartyReference",
        "FinalType" : {
          "@type" : "alfa.rt.model.UdtDataType",
          "FullyQualifiedName" : "FpML5.confirmation.PartyReference",
          "UdtType" : "recordType"
        }
      },
      "SrcLocation" : {
        "@type" : "alfa.rt.model.Location",
        "path" : "/Users/sadia/IdeaProjects/smt/utils/alfadocs/test/alfa/fpml/conf/fpml-main-5-9.alfa",
        "line" : 2712
      }
    },
    "payerAccountReference" : {
      "@type" : "alfa.rt.model.Field",
      "Doc" : "A reference to the account responsible for making the payments defined by this structure.",
      "Name" : "payerAccountReference",
      "DataType" : {
        "@type" : "alfa.rt.model.OptionalDataType",
        "ComponentType" : {
          "@type" : "alfa.rt.model.UdtDataType",
          "FullyQualifiedName" : "FpML5.confirmation.AccountReference",
          "UdtType" : "recordType"
        }
      },
      "SrcLocation" : {
        "@type" : "alfa.rt.model.Location",
        "path" : "/Users/sadia/IdeaProjects/smt/utils/alfadocs/test/alfa/fpml/conf/fpml-main-5-9.alfa",
        "line" : 2715
      }
    },
    "receiverPartyReference" : {
      "@type" : "alfa.rt.model.Field",
      "Doc" : "A reference to the party that receives the payments corresponding to this structure.",
      "Name" : "receiverPartyReference",
      "DataType" : {
        "@type" : "alfa.rt.model.UdtDataType",
        "FullyQualifiedName" : "FpML5.confirmation.PartyReference",
        "UdtType" : "recordType"
      },
      "DeclTypeDefDataType" : {
        "@type" : "alfa.rt.model.TypeDefDataType",
        "TypeName" : "FpML5.confirmation.PartyReference",
        "FinalType" : {
          "@type" : "alfa.rt.model.UdtDataType",
          "FullyQualifiedName" : "FpML5.confirmation.PartyReference",
          "UdtType" : "recordType"
        }
      },
      "SrcLocation" : {
        "@type" : "alfa.rt.model.Location",
        "path" : "/Users/sadia/IdeaProjects/smt/utils/alfadocs/test/alfa/fpml/conf/fpml-main-5-9.alfa",
        "line" : 2718
      }
    },
    "receiverAccountReference" : {
      "@type" : "alfa.rt.model.Field",
      "Doc" : "A reference to the account that receives the payments corresponding to this structure.",
      "Name" : "receiverAccountReference",
      "DataType" : {
        "@type" : "alfa.rt.model.OptionalDataType",
        "ComponentType" : {
          "@type" : "alfa.rt.model.UdtDataType",
          "FullyQualifiedName" : "FpML5.confirmation.AccountReference",
          "UdtType" : "recordType"
        }
      },
      "SrcLocation" : {
        "@type" : "alfa.rt.model.Location",
        "path" : "/Users/sadia/IdeaProjects/smt/utils/alfadocs/test/alfa/fpml/conf/fpml-main-5-9.alfa",
        "line" : 2721
      }
    },
    "calculationDates" : {
      "@type" : "alfa.rt.model.Field",
      "Doc" : "The Calculation Period dates for this leg of the trade where the Calculation Periods are all one day long. Only dates explicitly included determine the Calculation Periods and there is a Calculation Period for each date specified. As such one-day Calculation Period are typical a physically-settled emissions or metals trades it is expected that this element will not be used in performance swaps.",
      "Name" : "calculationDates",
      "DataType" : {
        "@type" : "alfa.rt.model.UdtDataType",
        "FullyQualifiedName" : "FpML5.confirmation.AdjustableDates",
        "UdtType" : "recordType"
      },
      "DeclTypeDefDataType" : {
        "@type" : "alfa.rt.model.TypeDefDataType",
        "TypeName" : "FpML5.confirmation.AdjustableDates",
        "FinalType" : {
          "@type" : "alfa.rt.model.UdtDataType",
          "FullyQualifiedName" : "FpML5.confirmation.AdjustableDates",
          "UdtType" : "recordType"
        }
      },
      "SrcLocation" : {
        "@type" : "alfa.rt.model.Location",
        "path" : "/Users/sadia/IdeaProjects/smt/utils/alfadocs/test/alfa/fpml/conf/fpml-main-5-9.alfa",
        "line" : 2724
      }
    },
    "calculationPeriods" : {
      "@type" : "alfa.rt.model.Field",
      "Doc" : "The Calculation Period start dates for this leg of the swap. This type is only intended to be used if the Calculation Periods differ on each leg. If Calculation Periods mirror another leg, then the calculationPeriodsReference element should be used to point to the Calculation Periods on that leg - or the calculationPeriodsScheduleReference can be used to point to the Calculation Periods Schedule for that leg.",
      "Name" : "calculationPeriods",
      "DataType" : {
        "@type" : "alfa.rt.model.UdtDataType",
        "FullyQualifiedName" : "FpML5.confirmation.AdjustableDates",
        "UdtType" : "recordType"
      },
      "DeclTypeDefDataType" : {
        "@type" : "alfa.rt.model.TypeDefDataType",
        "TypeName" : "FpML5.confirmation.AdjustableDates",
        "FinalType" : {
          "@type" : "alfa.rt.model.UdtDataType",
          "FullyQualifiedName" : "FpML5.confirmation.AdjustableDates",
          "UdtType" : "recordType"
        }
      },
      "SrcLocation" : {
        "@type" : "alfa.rt.model.Location",
        "path" : "/Users/sadia/IdeaProjects/smt/utils/alfadocs/test/alfa/fpml/conf/fpml-main-5-9.alfa",
        "line" : 2727
      }
    },
    "calculationPeriodsSchedule" : {
      "@type" : "alfa.rt.model.Field",
      "Doc" : "The Calculation Periods for this leg of the swap. This type is only intended to be used if the Calculation Periods differ on each leg. If Calculation Periods mirror another leg, then the calculationPeriodsReference element should be used to point to the Calculation Periods on the other leg - or the calculationPeriodsScheduleReference can be used to point to the Calculation Periods Schedule for that leg.",
      "Name" : "calculationPeriodsSchedule",
      "DataType" : {
        "@type" : "alfa.rt.model.UdtDataType",
        "FullyQualifiedName" : "FpML5.confirmation.CommodityCalculationPeriodsSchedule",
        "UdtType" : "recordType"
      },
      "DeclTypeDefDataType" : {
        "@type" : "alfa.rt.model.TypeDefDataType",
        "TypeName" : "FpML5.confirmation.CommodityCalculationPeriodsSchedule",
        "FinalType" : {
          "@type" : "alfa.rt.model.UdtDataType",
          "FullyQualifiedName" : "FpML5.confirmation.CommodityCalculationPeriodsSchedule",
          "UdtType" : "recordType"
        }
      },
      "SrcLocation" : {
        "@type" : "alfa.rt.model.Location",
        "path" : "/Users/sadia/IdeaProjects/smt/utils/alfadocs/test/alfa/fpml/conf/fpml-main-5-9.alfa",
        "line" : 2730
      }
    },
    "calculationPeriodsReference" : {
      "@type" : "alfa.rt.model.Field",
      "Doc" : "A pointer style reference to the Calculation Periods defined on another leg.",
      "Name" : "calculationPeriodsReference",
      "DataType" : {
        "@type" : "alfa.rt.model.UdtDataType",
        "FullyQualifiedName" : "FpML5.confirmation.CalculationPeriodsReference",
        "UdtType" : "recordType"
      },
      "DeclTypeDefDataType" : {
        "@type" : "alfa.rt.model.TypeDefDataType",
        "TypeName" : "FpML5.confirmation.CalculationPeriodsReference",
        "FinalType" : {
          "@type" : "alfa.rt.model.UdtDataType",
          "FullyQualifiedName" : "FpML5.confirmation.CalculationPeriodsReference",
          "UdtType" : "recordType"
        }
      },
      "SrcLocation" : {
        "@type" : "alfa.rt.model.Location",
        "path" : "/Users/sadia/IdeaProjects/smt/utils/alfadocs/test/alfa/fpml/conf/fpml-main-5-9.alfa",
        "line" : 2733
      }
    },
    "calculationPeriodsScheduleReference" : {
      "@type" : "alfa.rt.model.Field",
      "Doc" : "A pointer style reference to the Calculation Periods Schedule defined on another leg.",
      "Name" : "calculationPeriodsScheduleReference",
      "DataType" : {
        "@type" : "alfa.rt.model.UdtDataType",
        "FullyQualifiedName" : "FpML5.confirmation.CalculationPeriodsScheduleReference",
        "UdtType" : "recordType"
      },
      "DeclTypeDefDataType" : {
        "@type" : "alfa.rt.model.TypeDefDataType",
        "TypeName" : "FpML5.confirmation.CalculationPeriodsScheduleReference",
        "FinalType" : {
          "@type" : "alfa.rt.model.UdtDataType",
          "FullyQualifiedName" : "FpML5.confirmation.CalculationPeriodsScheduleReference",
          "UdtType" : "recordType"
        }
      },
      "SrcLocation" : {
        "@type" : "alfa.rt.model.Location",
        "path" : "/Users/sadia/IdeaProjects/smt/utils/alfadocs/test/alfa/fpml/conf/fpml-main-5-9.alfa",
        "line" : 2736
      }
    },
    "calculationPeriodsDatesReference" : {
      "@type" : "alfa.rt.model.Field",
      "Doc" : "A pointer style reference to single-day-duration Calculation Periods defined on another leg.",
      "Name" : "calculationPeriodsDatesReference",
      "DataType" : {
        "@type" : "alfa.rt.model.UdtDataType",
        "FullyQualifiedName" : "FpML5.confirmation.CalculationPeriodsDatesReference",
        "UdtType" : "recordType"
      },
      "DeclTypeDefDataType" : {
        "@type" : "alfa.rt.model.TypeDefDataType",
        "TypeName" : "FpML5.confirmation.CalculationPeriodsDatesReference",
        "FinalType" : {
          "@type" : "alfa.rt.model.UdtDataType",
          "FullyQualifiedName" : "FpML5.confirmation.CalculationPeriodsDatesReference",
          "UdtType" : "recordType"
        }
      },
      "SrcLocation" : {
        "@type" : "alfa.rt.model.Location",
        "path" : "/Users/sadia/IdeaProjects/smt/utils/alfadocs/test/alfa/fpml/conf/fpml-main-5-9.alfa",
        "line" : 2739
      }
    },
    "fixedPriceSchedule" : {
      "@type" : "alfa.rt.model.Field",
      "Doc" : "Allows the specification of a Fixed Price that varies over the life of the trade.",
      "Name" : "fixedPriceSchedule",
      "DataType" : {
        "@type" : "alfa.rt.model.UdtDataType",
        "FullyQualifiedName" : "FpML5.confirmation.CommodityFixedPriceSchedule",
        "UdtType" : "recordType"
      },
      "DeclTypeDefDataType" : {
        "@type" : "alfa.rt.model.TypeDefDataType",
        "TypeName" : "FpML5.confirmation.CommodityFixedPriceSchedule",
        "FinalType" : {
          "@type" : "alfa.rt.model.UdtDataType",
          "FullyQualifiedName" : "FpML5.confirmation.CommodityFixedPriceSchedule",
          "UdtType" : "recordType"
        }
      },
      "SrcLocation" : {
        "@type" : "alfa.rt.model.Location",
        "path" : "/Users/sadia/IdeaProjects/smt/utils/alfadocs/test/alfa/fpml/conf/fpml-main-5-9.alfa",
        "line" : 2742
      }
    },
    "fixedPrice" : {
      "@type" : "alfa.rt.model.Field",
      "Doc" : "Fixed price on which fixed payments are based.",
      "Name" : "fixedPrice",
      "DataType" : {
        "@type" : "alfa.rt.model.UdtDataType",
        "FullyQualifiedName" : "FpML5.confirmation.FixedPrice",
        "UdtType" : "recordType"
      },
      "DeclTypeDefDataType" : {
        "@type" : "alfa.rt.model.TypeDefDataType",
        "TypeName" : "FpML5.confirmation.FixedPrice",
        "FinalType" : {
          "@type" : "alfa.rt.model.UdtDataType",
          "FullyQualifiedName" : "FpML5.confirmation.FixedPrice",
          "UdtType" : "recordType"
        }
      },
      "SrcLocation" : {
        "@type" : "alfa.rt.model.Location",
        "path" : "/Users/sadia/IdeaProjects/smt/utils/alfadocs/test/alfa/fpml/conf/fpml-main-5-9.alfa",
        "line" : 2745
      }
    },
    "worldscaleRate" : {
      "@type" : "alfa.rt.model.Field",
      "Doc" : "For a WET Voyager Charter Commodity Swap, the number of Worldscale Points for purposes of the calculation of a Fixed Amount.",
      "Name" : "worldscaleRate",
      "DataType" : {
        "@type" : "alfa.rt.model.ScalarDataType",
        "ScalarType" : "decimalType"
      },
      "SrcLocation" : {
        "@type" : "alfa.rt.model.Location",
        "path" : "/Users/sadia/IdeaProjects/smt/utils/alfadocs/test/alfa/fpml/conf/fpml-main-5-9.alfa",
        "line" : 2748
      }
    },
    "contractRate" : {
      "@type" : "alfa.rt.model.Field",
      "Doc" : "For a DRY Voyage Charter or Time Charter Commodity Swap, the price per relevant unit for pruposes of the calculation of a Fixed Amount.",
      "Name" : "contractRate",
      "DataType" : {
        "@type" : "alfa.rt.model.UdtDataType",
        "FullyQualifiedName" : "FpML5.confirmation.NonNegativeMoney",
        "UdtType" : "recordType"
      },
      "DeclTypeDefDataType" : {
        "@type" : "alfa.rt.model.TypeDefDataType",
        "TypeName" : "FpML5.confirmation.NonNegativeMoney",
        "FinalType" : {
          "@type" : "alfa.rt.model.UdtDataType",
          "FullyQualifiedName" : "FpML5.confirmation.NonNegativeMoney",
          "UdtType" : "recordType"
        }
      },
      "SrcLocation" : {
        "@type" : "alfa.rt.model.Location",
        "path" : "/Users/sadia/IdeaProjects/smt/utils/alfadocs/test/alfa/fpml/conf/fpml-main-5-9.alfa",
        "line" : 2751
      }
    },
    "settlementPeriodsPrice" : {
      "@type" : "alfa.rt.model.Field",
      "Doc" : "For an electricity transaction, the fixed price for one or more groups of Settlement Periods on which fixed payments are based. If the fixed price differs for different groups of Settlement Periods, this element should be repeated.",
      "Name" : "settlementPeriodsPrice",
      "DataType" : {
        "@type" : "alfa.rt.model.UdtDataType",
        "FullyQualifiedName" : "FpML5.confirmation.SettlementPeriodsFixedPrice",
        "UdtType" : "recordType"
      },
      "DeclTypeDefDataType" : {
        "@type" : "alfa.rt.model.TypeDefDataType",
        "TypeName" : "FpML5.confirmation.SettlementPeriodsFixedPrice",
        "FinalType" : {
          "@type" : "alfa.rt.model.UdtDataType",
          "FullyQualifiedName" : "FpML5.confirmation.SettlementPeriodsFixedPrice",
          "UdtType" : "recordType"
        }
      },
      "SrcLocation" : {
        "@type" : "alfa.rt.model.Location",
        "path" : "/Users/sadia/IdeaProjects/smt/utils/alfadocs/test/alfa/fpml/conf/fpml-main-5-9.alfa",
        "line" : 2754
      }
    },
    "totalPrice" : {
      "@type" : "alfa.rt.model.Field",
      "Doc" : "The total amount of all fixed payments due during the term of the trade.",
      "Name" : "totalPrice",
      "DataType" : {
        "@type" : "alfa.rt.model.OptionalDataType",
        "ComponentType" : {
          "@type" : "alfa.rt.model.UdtDataType",
          "FullyQualifiedName" : "FpML5.confirmation.NonNegativeMoney",
          "UdtType" : "recordType"
        }
      },
      "SrcLocation" : {
        "@type" : "alfa.rt.model.Location",
        "path" : "/Users/sadia/IdeaProjects/smt/utils/alfadocs/test/alfa/fpml/conf/fpml-main-5-9.alfa",
        "line" : 2757
      }
    },
    "notionalQuantitySchedule" : {
      "@type" : "alfa.rt.model.Field",
      "Doc" : "Allows the documentation of a shaped notional trade where the notional changes over the life of the transaction.",
      "Name" : "notionalQuantitySchedule",
      "DataType" : {
        "@type" : "alfa.rt.model.UdtDataType",
        "FullyQualifiedName" : "FpML5.confirmation.CommodityNotionalQuantitySchedule",
        "UdtType" : "recordType"
      },
      "DeclTypeDefDataType" : {
        "@type" : "alfa.rt.model.TypeDefDataType",
        "TypeName" : "FpML5.confirmation.CommodityNotionalQuantitySchedule",
        "FinalType" : {
          "@type" : "alfa.rt.model.UdtDataType",
          "FullyQualifiedName" : "FpML5.confirmation.CommodityNotionalQuantitySchedule",
          "UdtType" : "recordType"
        }
      },
      "SrcLocation" : {
        "@type" : "alfa.rt.model.Location",
        "path" : "/Users/sadia/IdeaProjects/smt/utils/alfadocs/test/alfa/fpml/conf/fpml-main-5-9.alfa",
        "line" : 2760
      }
    },
    "notionalQuantity" : {
      "@type" : "alfa.rt.model.Field",
      "Doc" : "The Notional Quantity.",
      "Name" : "notionalQuantity",
      "DataType" : {
        "@type" : "alfa.rt.model.UdtDataType",
        "FullyQualifiedName" : "FpML5.confirmation.CommodityNotionalQuantity",
        "UdtType" : "recordType"
      },
      "DeclTypeDefDataType" : {
        "@type" : "alfa.rt.model.TypeDefDataType",
        "TypeName" : "FpML5.confirmation.CommodityNotionalQuantity",
        "FinalType" : {
          "@type" : "alfa.rt.model.UdtDataType",
          "FullyQualifiedName" : "FpML5.confirmation.CommodityNotionalQuantity",
          "UdtType" : "recordType"
        }
      },
      "SrcLocation" : {
        "@type" : "alfa.rt.model.Location",
        "path" : "/Users/sadia/IdeaProjects/smt/utils/alfadocs/test/alfa/fpml/conf/fpml-main-5-9.alfa",
        "line" : 2763
      }
    },
    "settlementPeriodsNotionalQuantity" : {
      "@type" : "alfa.rt.model.Field",
      "Doc" : "For an electricity transaction, the Notional Quantity for a one or more groups of Settlement Periods to which the Notional Quantity is based. If the schedule differs for different groups of Settlement Periods, this element should be repeated.",
      "Name" : "settlementPeriodsNotionalQuantity",
      "DataType" : {
        "@type" : "alfa.rt.model.UdtDataType",
        "FullyQualifiedName" : "FpML5.confirmation.CommoditySettlementPeriodsNotionalQuantity",
        "UdtType" : "recordType"
      },
      "DeclTypeDefDataType" : {
        "@type" : "alfa.rt.model.TypeDefDataType",
        "TypeName" : "FpML5.confirmation.CommoditySettlementPeriodsNotionalQuantity",
        "FinalType" : {
          "@type" : "alfa.rt.model.UdtDataType",
          "FullyQualifiedName" : "FpML5.confirmation.CommoditySettlementPeriodsNotionalQuantity",
          "UdtType" : "recordType"
        }
      },
      "SrcLocation" : {
        "@type" : "alfa.rt.model.Location",
        "path" : "/Users/sadia/IdeaProjects/smt/utils/alfadocs/test/alfa/fpml/conf/fpml-main-5-9.alfa",
        "line" : 2766
      }
    },
    "totalNotionalQuantity" : {
      "@type" : "alfa.rt.model.Field",
      "Doc" : "The Total Notional Quantity.",
      "Name" : "totalNotionalQuantity",
      "DataType" : {
        "@type" : "alfa.rt.model.OptionalDataType",
        "ComponentType" : {
          "@type" : "alfa.rt.model.ScalarDataType",
          "ScalarType" : "decimalType"
        }
      },
      "SrcLocation" : {
        "@type" : "alfa.rt.model.Location",
        "path" : "/Users/sadia/IdeaProjects/smt/utils/alfadocs/test/alfa/fpml/conf/fpml-main-5-9.alfa",
        "line" : 2769
      }
    },
    "quantityReference" : {
      "@type" : "alfa.rt.model.Field",
      "Doc" : "A pointer style reference to a quantity defined on another leg.",
      "Name" : "quantityReference",
      "DataType" : {
        "@type" : "alfa.rt.model.UdtDataType",
        "FullyQualifiedName" : "FpML5.confirmation.QuantityReference",
        "UdtType" : "recordType"
      },
      "DeclTypeDefDataType" : {
        "@type" : "alfa.rt.model.TypeDefDataType",
        "TypeName" : "FpML5.confirmation.QuantityReference",
        "FinalType" : {
          "@type" : "alfa.rt.model.UdtDataType",
          "FullyQualifiedName" : "FpML5.confirmation.QuantityReference",
          "UdtType" : "recordType"
        }
      },
      "SrcLocation" : {
        "@type" : "alfa.rt.model.Location",
        "path" : "/Users/sadia/IdeaProjects/smt/utils/alfadocs/test/alfa/fpml/conf/fpml-main-5-9.alfa",
        "line" : 2772
      }
    },
    "relativePaymentDates" : {
      "@type" : "alfa.rt.model.Field",
      "Doc" : "The Payment Dates of the trade relative to the Calculation Periods.",
      "Name" : "relativePaymentDates",
      "DataType" : {
        "@type" : "alfa.rt.model.UdtDataType",
        "FullyQualifiedName" : "FpML5.confirmation.CommodityRelativePaymentDates",
        "UdtType" : "recordType"
      },
      "DeclTypeDefDataType" : {
        "@type" : "alfa.rt.model.TypeDefDataType",
        "TypeName" : "FpML5.confirmation.CommodityRelativePaymentDates",
        "FinalType" : {
          "@type" : "alfa.rt.model.UdtDataType",
          "FullyQualifiedName" : "FpML5.confirmation.CommodityRelativePaymentDates",
          "UdtType" : "recordType"
        }
      },
      "SrcLocation" : {
        "@type" : "alfa.rt.model.Location",
        "path" : "/Users/sadia/IdeaProjects/smt/utils/alfadocs/test/alfa/fpml/conf/fpml-main-5-9.alfa",
        "line" : 2775
      }
    },
    "paymentDates" : {
      "@type" : "alfa.rt.model.Field",
      "Doc" : "Dates on which payments will be made.",
      "Name" : "paymentDates",
      "DataType" : {
        "@type" : "alfa.rt.model.UdtDataType",
        "FullyQualifiedName" : "FpML5.confirmation.AdjustableDatesOrRelativeDateOffset",
        "UdtType" : "recordType"
      },
      "DeclTypeDefDataType" : {
        "@type" : "alfa.rt.model.TypeDefDataType",
        "TypeName" : "FpML5.confirmation.AdjustableDatesOrRelativeDateOffset",
        "FinalType" : {
          "@type" : "alfa.rt.model.UdtDataType",
          "FullyQualifiedName" : "FpML5.confirmation.AdjustableDatesOrRelativeDateOffset",
          "UdtType" : "recordType"
        }
      },
      "SrcLocation" : {
        "@type" : "alfa.rt.model.Location",
        "path" : "/Users/sadia/IdeaProjects/smt/utils/alfadocs/test/alfa/fpml/conf/fpml-main-5-9.alfa",
        "line" : 2778
      }
    },
    "masterAgreementPaymentDates" : {
      "@type" : "alfa.rt.model.Field",
      "Doc" : "If present and true indicates that the Payment Date(s) are specified in the relevant master agreement.",
      "Name" : "masterAgreementPaymentDates",
      "DataType" : {
        "@type" : "alfa.rt.model.ScalarDataType",
        "ScalarType" : "booleanType"
      },
      "SrcLocation" : {
        "@type" : "alfa.rt.model.Location",
        "path" : "/Users/sadia/IdeaProjects/smt/utils/alfadocs/test/alfa/fpml/conf/fpml-main-5-9.alfa",
        "line" : 2781
      }
    },
    "flatRate" : {
      "@type" : "alfa.rt.model.Field",
      "Doc" : "Whether the Flat Rate is the New Worldwide Tanker Nominal Freight Scale for the Freight Index Route taken at the Trade Date of the transaction or taken on each Pricing Date.",
      "Name" : "flatRate",
      "DataType" : {
        "@type" : "alfa.rt.model.ScalarDataType",
        "ScalarType" : "stringType"
      },
      "SrcLocation" : {
        "@type" : "alfa.rt.model.Location",
        "path" : "/Users/sadia/IdeaProjects/smt/utils/alfadocs/test/alfa/fpml/conf/fpml-main-5-9.alfa",
        "line" : 2784
      }
    },
    "flatRateAmount" : {
      "@type" : "alfa.rt.model.Field",
      "Doc" : "If flatRate is set to \"Fixed\", the actual value of the Flat Rate.",
      "Name" : "flatRateAmount",
      "DataType" : {
        "@type" : "alfa.rt.model.OptionalDataType",
        "ComponentType" : {
          "@type" : "alfa.rt.model.UdtDataType",
          "FullyQualifiedName" : "FpML5.confirmation.NonNegativeMoney",
          "UdtType" : "recordType"
        }
      },
      "SrcLocation" : {
        "@type" : "alfa.rt.model.Location",
        "path" : "/Users/sadia/IdeaProjects/smt/utils/alfadocs/test/alfa/fpml/conf/fpml-main-5-9.alfa",
        "line" : 2787
      }
    },
    "id" : {
      "@type" : "alfa.rt.model.Field",
      "Name" : "id",
      "DataType" : {
        "@type" : "alfa.rt.model.OptionalDataType",
        "ComponentType" : {
          "@type" : "alfa.rt.model.ScalarDataType",
          "ScalarType" : "stringType"
        }
      },
      "SrcLocation" : {
        "@type" : "alfa.rt.model.Location",
        "path" : "/Users/sadia/IdeaProjects/smt/utils/alfadocs/test/alfa/fpml/conf/fpml-main-5-9.alfa",
        "line" : 2790
      }
    }
  },
  "LocalFieldNames" : [ "payerPartyReference", "payerAccountReference", "receiverPartyReference", "receiverAccountReference", "calculationDates", "calculationPeriods", "calculationPeriodsSchedule", "calculationPeriodsReference", "calculationPeriodsScheduleReference", "calculationPeriodsDatesReference", "fixedPriceSchedule", "fixedPrice", "worldscaleRate", "contractRate", "settlementPeriodsPrice", "totalPrice", "notionalQuantitySchedule", "notionalQuantity", "settlementPeriodsNotionalQuantity", "totalNotionalQuantity", "quantityReference", "relativePaymentDates", "paymentDates", "masterAgreementPaymentDates", "flatRate", "flatRateAmount", "id" ],
  "IsSynthetic" : false
}