{
  "@type" : "alfa.rt.model.Record",
  "Doc" : "Floating Price Leg of a Commodity Swap. Each 'floatingLeg' defines a series of financial payments for a commodity the value of which is derived from a floating price such as an exchange or an index publication.",
  "Name" : {
    "@type" : "alfa.rt.model.UdtVersionedName",
    "FullyQualifiedName" : "FpML5.recordkeeping.FloatingPriceLeg",
    "UdtType" : "recordType"
  },
  "Includes" : [ ],
  "Source" : {
    "@type" : "alfa.rt.model.Union__ModelBaseNode_Source",
    "Contents" : "/#\n   Floating Price Leg of a Commodity Swap. Each 'floatingLeg' defines a series of financial payments for a commodity the value of which is derived from a floating price such as an exchange or an index publication.\n #/\nrecord FpML5.recordkeeping.FloatingPriceLeg {\n  # A reference to the party responsible for making the payments defined by this structure.\n  payerPartyReference : FpML5.recordkeeping.PartyReference\n\n  # A reference to the account responsible for making the payments defined by this structure.\n  payerAccountReference : FpML5.recordkeeping.AccountReference?\n\n  # A reference to the party that receives the payments corresponding to this structure.\n  receiverPartyReference : FpML5.recordkeeping.PartyReference?\n\n  # A reference to the account that receives the payments corresponding to this structure.\n  receiverAccountReference : FpML5.recordkeeping.AccountReference?\n\n  # The Calculation Period dates for this leg of the trade where the Calculation Periods are all one day long. Only dates explicitly included determine the Calculation Periods and there is a Calculation Period for each date specified. As such one-day Calculation Period are typical a physically-settled emissions or metals trades it is expected that this element will not be used in performance swaps.\n  calculationDates : FpML5.recordkeeping.AdjustableDates\n\n  # The Calculation Period start dates for this leg of the swap. This type is only intended to be used if the Calculation Periods differ on each leg. If Calculation Periods mirror another leg, then the calculationPeriodsReference element should be used to point to the Calculation Periods on that leg - or the calculationPeriodsScheduleReference can be used to point to the Calculation Periods Schedule for that leg.\n  calculationPeriods : FpML5.recordkeeping.AdjustableDates\n\n  # The Calculation Periods for this leg of the swap. This type is only intended to be used if the Calculation Periods differ on each leg. If Calculation Periods mirror another leg, then the calculationPeriodsReference element should be used to point to the Calculation Periods on the other leg - or the calculationPeriodsScheduleReference can be used to point to the Calculation Periods Schedule for that leg.\n  calculationPeriodsSchedule : FpML5.recordkeeping.CommodityCalculationPeriodsSchedule\n\n  # A pointer style reference to the Calculation Periods defined on another leg.\n  calculationPeriodsReference : FpML5.recordkeeping.CalculationPeriodsReference\n\n  # A pointer style reference to the Calculation Periods Schedule defined on another leg.\n  calculationPeriodsScheduleReference : FpML5.recordkeeping.CalculationPeriodsScheduleReference\n\n  # A pointer style reference to single-day-duration Calculation Periods defined on another leg.\n  calculationPeriodsDatesReference : FpML5.recordkeeping.CalculationPeriodsDatesReference\n\n  # Specifies the underlying instrument. Only underlyers of type Commodity are supported.\n  commodity : FpML5.recordkeeping.Commodity\n\n  # Allows the documentation of a shaped notional trade where the notional changes over the life of the transaction.\n  notionalQuantitySchedule : FpML5.recordkeeping.CommodityNotionalQuantitySchedule\n\n  # The Notional Quantity.\n  notionalQuantity : FpML5.recordkeeping.CommodityNotionalQuantity\n\n  # For an electricity transaction, the Notional Quantity for a one or more groups of Settlement Periods to which the Notional Quantity is based. If the schedule differs for different groups of Settlement Periods, this element should be repeated.\n  settlementPeriodsNotionalQuantity : FpML5.recordkeeping.CommoditySettlementPeriodsNotionalQuantity\n\n  # The Total Notional Quantity.\n  totalNotionalQuantity : decimal\n\n  # A pointer style reference to a quantity defined on another leg.\n  quantityReference : FpML5.recordkeeping.QuantityReference\n\n  # Defines details relevant to the calculation of the floating price.\n  calculation : FpML5.recordkeeping.FloatingLegCalculation\n\n  # The Payment Dates of the trade relative to the Calculation Periods.\n  relativePaymentDates : FpML5.recordkeeping.CommodityRelativePaymentDates\n\n  # Dates on which payments will be made.\n  paymentDates : FpML5.recordkeeping.AdjustableDatesOrRelativeDateOffset\n\n  # If present and true indicates that the Payment Date(s) are specified in the relevant master agreement.\n  masterAgreementPaymentDates : boolean\n\n  # Whether the Flat Rate is the New Worldwide Tanker Nominal Freight Scale for the Freight Index Route taken at the Trade Date of the transaction or taken on each Pricing Date.\n  flatRate : string?\n\n  # If flatRate is set to \"Fixed\", the actual value of the Flat Rate.\n  flatRateAmount : FpML5.recordkeeping.NonNegativeMoney?\n\n  id : string?\n\n}"
  },
  "AllFields" : {
    "payerPartyReference" : {
      "@type" : "alfa.rt.model.Field",
      "Doc" : "A reference to the party responsible for making the payments defined by this structure.",
      "Name" : "payerPartyReference",
      "DataType" : {
        "@type" : "alfa.rt.model.UdtDataType",
        "FullyQualifiedName" : "FpML5.recordkeeping.PartyReference",
        "UdtType" : "recordType"
      },
      "DeclTypeDefDataType" : {
        "@type" : "alfa.rt.model.TypeDefDataType",
        "TypeName" : "FpML5.recordkeeping.PartyReference",
        "FinalType" : {
          "@type" : "alfa.rt.model.UdtDataType",
          "FullyQualifiedName" : "FpML5.recordkeeping.PartyReference",
          "UdtType" : "recordType"
        }
      },
      "SrcLocation" : {
        "@type" : "alfa.rt.model.Location",
        "path" : "/Users/sadia/IdeaProjects/smt/utils/alfadocs/test/alfa/fpml/rk/fpml-main-5-9.alfa",
        "line" : 2187
      }
    },
    "payerAccountReference" : {
      "@type" : "alfa.rt.model.Field",
      "Doc" : "A reference to the account responsible for making the payments defined by this structure.",
      "Name" : "payerAccountReference",
      "DataType" : {
        "@type" : "alfa.rt.model.OptionalDataType",
        "ComponentType" : {
          "@type" : "alfa.rt.model.UdtDataType",
          "FullyQualifiedName" : "FpML5.recordkeeping.AccountReference",
          "UdtType" : "recordType"
        }
      },
      "SrcLocation" : {
        "@type" : "alfa.rt.model.Location",
        "path" : "/Users/sadia/IdeaProjects/smt/utils/alfadocs/test/alfa/fpml/rk/fpml-main-5-9.alfa",
        "line" : 2190
      }
    },
    "receiverPartyReference" : {
      "@type" : "alfa.rt.model.Field",
      "Doc" : "A reference to the party that receives the payments corresponding to this structure.",
      "Name" : "receiverPartyReference",
      "DataType" : {
        "@type" : "alfa.rt.model.OptionalDataType",
        "ComponentType" : {
          "@type" : "alfa.rt.model.UdtDataType",
          "FullyQualifiedName" : "FpML5.recordkeeping.PartyReference",
          "UdtType" : "recordType"
        }
      },
      "SrcLocation" : {
        "@type" : "alfa.rt.model.Location",
        "path" : "/Users/sadia/IdeaProjects/smt/utils/alfadocs/test/alfa/fpml/rk/fpml-main-5-9.alfa",
        "line" : 2193
      }
    },
    "receiverAccountReference" : {
      "@type" : "alfa.rt.model.Field",
      "Doc" : "A reference to the account that receives the payments corresponding to this structure.",
      "Name" : "receiverAccountReference",
      "DataType" : {
        "@type" : "alfa.rt.model.OptionalDataType",
        "ComponentType" : {
          "@type" : "alfa.rt.model.UdtDataType",
          "FullyQualifiedName" : "FpML5.recordkeeping.AccountReference",
          "UdtType" : "recordType"
        }
      },
      "SrcLocation" : {
        "@type" : "alfa.rt.model.Location",
        "path" : "/Users/sadia/IdeaProjects/smt/utils/alfadocs/test/alfa/fpml/rk/fpml-main-5-9.alfa",
        "line" : 2196
      }
    },
    "calculationDates" : {
      "@type" : "alfa.rt.model.Field",
      "Doc" : "The Calculation Period dates for this leg of the trade where the Calculation Periods are all one day long. Only dates explicitly included determine the Calculation Periods and there is a Calculation Period for each date specified. As such one-day Calculation Period are typical a physically-settled emissions or metals trades it is expected that this element will not be used in performance swaps.",
      "Name" : "calculationDates",
      "DataType" : {
        "@type" : "alfa.rt.model.UdtDataType",
        "FullyQualifiedName" : "FpML5.recordkeeping.AdjustableDates",
        "UdtType" : "recordType"
      },
      "DeclTypeDefDataType" : {
        "@type" : "alfa.rt.model.TypeDefDataType",
        "TypeName" : "FpML5.recordkeeping.AdjustableDates",
        "FinalType" : {
          "@type" : "alfa.rt.model.UdtDataType",
          "FullyQualifiedName" : "FpML5.recordkeeping.AdjustableDates",
          "UdtType" : "recordType"
        }
      },
      "SrcLocation" : {
        "@type" : "alfa.rt.model.Location",
        "path" : "/Users/sadia/IdeaProjects/smt/utils/alfadocs/test/alfa/fpml/rk/fpml-main-5-9.alfa",
        "line" : 2199
      }
    },
    "calculationPeriods" : {
      "@type" : "alfa.rt.model.Field",
      "Doc" : "The Calculation Period start dates for this leg of the swap. This type is only intended to be used if the Calculation Periods differ on each leg. If Calculation Periods mirror another leg, then the calculationPeriodsReference element should be used to point to the Calculation Periods on that leg - or the calculationPeriodsScheduleReference can be used to point to the Calculation Periods Schedule for that leg.",
      "Name" : "calculationPeriods",
      "DataType" : {
        "@type" : "alfa.rt.model.UdtDataType",
        "FullyQualifiedName" : "FpML5.recordkeeping.AdjustableDates",
        "UdtType" : "recordType"
      },
      "DeclTypeDefDataType" : {
        "@type" : "alfa.rt.model.TypeDefDataType",
        "TypeName" : "FpML5.recordkeeping.AdjustableDates",
        "FinalType" : {
          "@type" : "alfa.rt.model.UdtDataType",
          "FullyQualifiedName" : "FpML5.recordkeeping.AdjustableDates",
          "UdtType" : "recordType"
        }
      },
      "SrcLocation" : {
        "@type" : "alfa.rt.model.Location",
        "path" : "/Users/sadia/IdeaProjects/smt/utils/alfadocs/test/alfa/fpml/rk/fpml-main-5-9.alfa",
        "line" : 2202
      }
    },
    "calculationPeriodsSchedule" : {
      "@type" : "alfa.rt.model.Field",
      "Doc" : "The Calculation Periods for this leg of the swap. This type is only intended to be used if the Calculation Periods differ on each leg. If Calculation Periods mirror another leg, then the calculationPeriodsReference element should be used to point to the Calculation Periods on the other leg - or the calculationPeriodsScheduleReference can be used to point to the Calculation Periods Schedule for that leg.",
      "Name" : "calculationPeriodsSchedule",
      "DataType" : {
        "@type" : "alfa.rt.model.UdtDataType",
        "FullyQualifiedName" : "FpML5.recordkeeping.CommodityCalculationPeriodsSchedule",
        "UdtType" : "recordType"
      },
      "DeclTypeDefDataType" : {
        "@type" : "alfa.rt.model.TypeDefDataType",
        "TypeName" : "FpML5.recordkeeping.CommodityCalculationPeriodsSchedule",
        "FinalType" : {
          "@type" : "alfa.rt.model.UdtDataType",
          "FullyQualifiedName" : "FpML5.recordkeeping.CommodityCalculationPeriodsSchedule",
          "UdtType" : "recordType"
        }
      },
      "SrcLocation" : {
        "@type" : "alfa.rt.model.Location",
        "path" : "/Users/sadia/IdeaProjects/smt/utils/alfadocs/test/alfa/fpml/rk/fpml-main-5-9.alfa",
        "line" : 2205
      }
    },
    "calculationPeriodsReference" : {
      "@type" : "alfa.rt.model.Field",
      "Doc" : "A pointer style reference to the Calculation Periods defined on another leg.",
      "Name" : "calculationPeriodsReference",
      "DataType" : {
        "@type" : "alfa.rt.model.UdtDataType",
        "FullyQualifiedName" : "FpML5.recordkeeping.CalculationPeriodsReference",
        "UdtType" : "recordType"
      },
      "DeclTypeDefDataType" : {
        "@type" : "alfa.rt.model.TypeDefDataType",
        "TypeName" : "FpML5.recordkeeping.CalculationPeriodsReference",
        "FinalType" : {
          "@type" : "alfa.rt.model.UdtDataType",
          "FullyQualifiedName" : "FpML5.recordkeeping.CalculationPeriodsReference",
          "UdtType" : "recordType"
        }
      },
      "SrcLocation" : {
        "@type" : "alfa.rt.model.Location",
        "path" : "/Users/sadia/IdeaProjects/smt/utils/alfadocs/test/alfa/fpml/rk/fpml-main-5-9.alfa",
        "line" : 2208
      }
    },
    "calculationPeriodsScheduleReference" : {
      "@type" : "alfa.rt.model.Field",
      "Doc" : "A pointer style reference to the Calculation Periods Schedule defined on another leg.",
      "Name" : "calculationPeriodsScheduleReference",
      "DataType" : {
        "@type" : "alfa.rt.model.UdtDataType",
        "FullyQualifiedName" : "FpML5.recordkeeping.CalculationPeriodsScheduleReference",
        "UdtType" : "recordType"
      },
      "DeclTypeDefDataType" : {
        "@type" : "alfa.rt.model.TypeDefDataType",
        "TypeName" : "FpML5.recordkeeping.CalculationPeriodsScheduleReference",
        "FinalType" : {
          "@type" : "alfa.rt.model.UdtDataType",
          "FullyQualifiedName" : "FpML5.recordkeeping.CalculationPeriodsScheduleReference",
          "UdtType" : "recordType"
        }
      },
      "SrcLocation" : {
        "@type" : "alfa.rt.model.Location",
        "path" : "/Users/sadia/IdeaProjects/smt/utils/alfadocs/test/alfa/fpml/rk/fpml-main-5-9.alfa",
        "line" : 2211
      }
    },
    "calculationPeriodsDatesReference" : {
      "@type" : "alfa.rt.model.Field",
      "Doc" : "A pointer style reference to single-day-duration Calculation Periods defined on another leg.",
      "Name" : "calculationPeriodsDatesReference",
      "DataType" : {
        "@type" : "alfa.rt.model.UdtDataType",
        "FullyQualifiedName" : "FpML5.recordkeeping.CalculationPeriodsDatesReference",
        "UdtType" : "recordType"
      },
      "DeclTypeDefDataType" : {
        "@type" : "alfa.rt.model.TypeDefDataType",
        "TypeName" : "FpML5.recordkeeping.CalculationPeriodsDatesReference",
        "FinalType" : {
          "@type" : "alfa.rt.model.UdtDataType",
          "FullyQualifiedName" : "FpML5.recordkeeping.CalculationPeriodsDatesReference",
          "UdtType" : "recordType"
        }
      },
      "SrcLocation" : {
        "@type" : "alfa.rt.model.Location",
        "path" : "/Users/sadia/IdeaProjects/smt/utils/alfadocs/test/alfa/fpml/rk/fpml-main-5-9.alfa",
        "line" : 2214
      }
    },
    "commodity" : {
      "@type" : "alfa.rt.model.Field",
      "Doc" : "Specifies the underlying instrument. Only underlyers of type Commodity are supported.",
      "Name" : "commodity",
      "DataType" : {
        "@type" : "alfa.rt.model.UdtDataType",
        "FullyQualifiedName" : "FpML5.recordkeeping.Commodity",
        "UdtType" : "recordType"
      },
      "DeclTypeDefDataType" : {
        "@type" : "alfa.rt.model.TypeDefDataType",
        "TypeName" : "FpML5.recordkeeping.Commodity",
        "FinalType" : {
          "@type" : "alfa.rt.model.UdtDataType",
          "FullyQualifiedName" : "FpML5.recordkeeping.Commodity",
          "UdtType" : "recordType"
        }
      },
      "SrcLocation" : {
        "@type" : "alfa.rt.model.Location",
        "path" : "/Users/sadia/IdeaProjects/smt/utils/alfadocs/test/alfa/fpml/rk/fpml-main-5-9.alfa",
        "line" : 2217
      }
    },
    "notionalQuantitySchedule" : {
      "@type" : "alfa.rt.model.Field",
      "Doc" : "Allows the documentation of a shaped notional trade where the notional changes over the life of the transaction.",
      "Name" : "notionalQuantitySchedule",
      "DataType" : {
        "@type" : "alfa.rt.model.UdtDataType",
        "FullyQualifiedName" : "FpML5.recordkeeping.CommodityNotionalQuantitySchedule",
        "UdtType" : "recordType"
      },
      "DeclTypeDefDataType" : {
        "@type" : "alfa.rt.model.TypeDefDataType",
        "TypeName" : "FpML5.recordkeeping.CommodityNotionalQuantitySchedule",
        "FinalType" : {
          "@type" : "alfa.rt.model.UdtDataType",
          "FullyQualifiedName" : "FpML5.recordkeeping.CommodityNotionalQuantitySchedule",
          "UdtType" : "recordType"
        }
      },
      "SrcLocation" : {
        "@type" : "alfa.rt.model.Location",
        "path" : "/Users/sadia/IdeaProjects/smt/utils/alfadocs/test/alfa/fpml/rk/fpml-main-5-9.alfa",
        "line" : 2220
      }
    },
    "notionalQuantity" : {
      "@type" : "alfa.rt.model.Field",
      "Doc" : "The Notional Quantity.",
      "Name" : "notionalQuantity",
      "DataType" : {
        "@type" : "alfa.rt.model.UdtDataType",
        "FullyQualifiedName" : "FpML5.recordkeeping.CommodityNotionalQuantity",
        "UdtType" : "recordType"
      },
      "DeclTypeDefDataType" : {
        "@type" : "alfa.rt.model.TypeDefDataType",
        "TypeName" : "FpML5.recordkeeping.CommodityNotionalQuantity",
        "FinalType" : {
          "@type" : "alfa.rt.model.UdtDataType",
          "FullyQualifiedName" : "FpML5.recordkeeping.CommodityNotionalQuantity",
          "UdtType" : "recordType"
        }
      },
      "SrcLocation" : {
        "@type" : "alfa.rt.model.Location",
        "path" : "/Users/sadia/IdeaProjects/smt/utils/alfadocs/test/alfa/fpml/rk/fpml-main-5-9.alfa",
        "line" : 2223
      }
    },
    "settlementPeriodsNotionalQuantity" : {
      "@type" : "alfa.rt.model.Field",
      "Doc" : "For an electricity transaction, the Notional Quantity for a one or more groups of Settlement Periods to which the Notional Quantity is based. If the schedule differs for different groups of Settlement Periods, this element should be repeated.",
      "Name" : "settlementPeriodsNotionalQuantity",
      "DataType" : {
        "@type" : "alfa.rt.model.UdtDataType",
        "FullyQualifiedName" : "FpML5.recordkeeping.CommoditySettlementPeriodsNotionalQuantity",
        "UdtType" : "recordType"
      },
      "DeclTypeDefDataType" : {
        "@type" : "alfa.rt.model.TypeDefDataType",
        "TypeName" : "FpML5.recordkeeping.CommoditySettlementPeriodsNotionalQuantity",
        "FinalType" : {
          "@type" : "alfa.rt.model.UdtDataType",
          "FullyQualifiedName" : "FpML5.recordkeeping.CommoditySettlementPeriodsNotionalQuantity",
          "UdtType" : "recordType"
        }
      },
      "SrcLocation" : {
        "@type" : "alfa.rt.model.Location",
        "path" : "/Users/sadia/IdeaProjects/smt/utils/alfadocs/test/alfa/fpml/rk/fpml-main-5-9.alfa",
        "line" : 2226
      }
    },
    "totalNotionalQuantity" : {
      "@type" : "alfa.rt.model.Field",
      "Doc" : "The Total Notional Quantity.",
      "Name" : "totalNotionalQuantity",
      "DataType" : {
        "@type" : "alfa.rt.model.ScalarDataType",
        "ScalarType" : "decimalType"
      },
      "SrcLocation" : {
        "@type" : "alfa.rt.model.Location",
        "path" : "/Users/sadia/IdeaProjects/smt/utils/alfadocs/test/alfa/fpml/rk/fpml-main-5-9.alfa",
        "line" : 2229
      }
    },
    "quantityReference" : {
      "@type" : "alfa.rt.model.Field",
      "Doc" : "A pointer style reference to a quantity defined on another leg.",
      "Name" : "quantityReference",
      "DataType" : {
        "@type" : "alfa.rt.model.UdtDataType",
        "FullyQualifiedName" : "FpML5.recordkeeping.QuantityReference",
        "UdtType" : "recordType"
      },
      "DeclTypeDefDataType" : {
        "@type" : "alfa.rt.model.TypeDefDataType",
        "TypeName" : "FpML5.recordkeeping.QuantityReference",
        "FinalType" : {
          "@type" : "alfa.rt.model.UdtDataType",
          "FullyQualifiedName" : "FpML5.recordkeeping.QuantityReference",
          "UdtType" : "recordType"
        }
      },
      "SrcLocation" : {
        "@type" : "alfa.rt.model.Location",
        "path" : "/Users/sadia/IdeaProjects/smt/utils/alfadocs/test/alfa/fpml/rk/fpml-main-5-9.alfa",
        "line" : 2232
      }
    },
    "calculation" : {
      "@type" : "alfa.rt.model.Field",
      "Doc" : "Defines details relevant to the calculation of the floating price.",
      "Name" : "calculation",
      "DataType" : {
        "@type" : "alfa.rt.model.UdtDataType",
        "FullyQualifiedName" : "FpML5.recordkeeping.FloatingLegCalculation",
        "UdtType" : "recordType"
      },
      "DeclTypeDefDataType" : {
        "@type" : "alfa.rt.model.TypeDefDataType",
        "TypeName" : "FpML5.recordkeeping.FloatingLegCalculation",
        "FinalType" : {
          "@type" : "alfa.rt.model.UdtDataType",
          "FullyQualifiedName" : "FpML5.recordkeeping.FloatingLegCalculation",
          "UdtType" : "recordType"
        }
      },
      "SrcLocation" : {
        "@type" : "alfa.rt.model.Location",
        "path" : "/Users/sadia/IdeaProjects/smt/utils/alfadocs/test/alfa/fpml/rk/fpml-main-5-9.alfa",
        "line" : 2235
      }
    },
    "relativePaymentDates" : {
      "@type" : "alfa.rt.model.Field",
      "Doc" : "The Payment Dates of the trade relative to the Calculation Periods.",
      "Name" : "relativePaymentDates",
      "DataType" : {
        "@type" : "alfa.rt.model.UdtDataType",
        "FullyQualifiedName" : "FpML5.recordkeeping.CommodityRelativePaymentDates",
        "UdtType" : "recordType"
      },
      "DeclTypeDefDataType" : {
        "@type" : "alfa.rt.model.TypeDefDataType",
        "TypeName" : "FpML5.recordkeeping.CommodityRelativePaymentDates",
        "FinalType" : {
          "@type" : "alfa.rt.model.UdtDataType",
          "FullyQualifiedName" : "FpML5.recordkeeping.CommodityRelativePaymentDates",
          "UdtType" : "recordType"
        }
      },
      "SrcLocation" : {
        "@type" : "alfa.rt.model.Location",
        "path" : "/Users/sadia/IdeaProjects/smt/utils/alfadocs/test/alfa/fpml/rk/fpml-main-5-9.alfa",
        "line" : 2238
      }
    },
    "paymentDates" : {
      "@type" : "alfa.rt.model.Field",
      "Doc" : "Dates on which payments will be made.",
      "Name" : "paymentDates",
      "DataType" : {
        "@type" : "alfa.rt.model.UdtDataType",
        "FullyQualifiedName" : "FpML5.recordkeeping.AdjustableDatesOrRelativeDateOffset",
        "UdtType" : "recordType"
      },
      "DeclTypeDefDataType" : {
        "@type" : "alfa.rt.model.TypeDefDataType",
        "TypeName" : "FpML5.recordkeeping.AdjustableDatesOrRelativeDateOffset",
        "FinalType" : {
          "@type" : "alfa.rt.model.UdtDataType",
          "FullyQualifiedName" : "FpML5.recordkeeping.AdjustableDatesOrRelativeDateOffset",
          "UdtType" : "recordType"
        }
      },
      "SrcLocation" : {
        "@type" : "alfa.rt.model.Location",
        "path" : "/Users/sadia/IdeaProjects/smt/utils/alfadocs/test/alfa/fpml/rk/fpml-main-5-9.alfa",
        "line" : 2241
      }
    },
    "masterAgreementPaymentDates" : {
      "@type" : "alfa.rt.model.Field",
      "Doc" : "If present and true indicates that the Payment Date(s) are specified in the relevant master agreement.",
      "Name" : "masterAgreementPaymentDates",
      "DataType" : {
        "@type" : "alfa.rt.model.ScalarDataType",
        "ScalarType" : "booleanType"
      },
      "SrcLocation" : {
        "@type" : "alfa.rt.model.Location",
        "path" : "/Users/sadia/IdeaProjects/smt/utils/alfadocs/test/alfa/fpml/rk/fpml-main-5-9.alfa",
        "line" : 2244
      }
    },
    "flatRate" : {
      "@type" : "alfa.rt.model.Field",
      "Doc" : "Whether the Flat Rate is the New Worldwide Tanker Nominal Freight Scale for the Freight Index Route taken at the Trade Date of the transaction or taken on each Pricing Date.",
      "Name" : "flatRate",
      "DataType" : {
        "@type" : "alfa.rt.model.OptionalDataType",
        "ComponentType" : {
          "@type" : "alfa.rt.model.ScalarDataType",
          "ScalarType" : "stringType"
        }
      },
      "SrcLocation" : {
        "@type" : "alfa.rt.model.Location",
        "path" : "/Users/sadia/IdeaProjects/smt/utils/alfadocs/test/alfa/fpml/rk/fpml-main-5-9.alfa",
        "line" : 2247
      }
    },
    "flatRateAmount" : {
      "@type" : "alfa.rt.model.Field",
      "Doc" : "If flatRate is set to \"Fixed\", the actual value of the Flat Rate.",
      "Name" : "flatRateAmount",
      "DataType" : {
        "@type" : "alfa.rt.model.OptionalDataType",
        "ComponentType" : {
          "@type" : "alfa.rt.model.UdtDataType",
          "FullyQualifiedName" : "FpML5.recordkeeping.NonNegativeMoney",
          "UdtType" : "recordType"
        }
      },
      "SrcLocation" : {
        "@type" : "alfa.rt.model.Location",
        "path" : "/Users/sadia/IdeaProjects/smt/utils/alfadocs/test/alfa/fpml/rk/fpml-main-5-9.alfa",
        "line" : 2250
      }
    },
    "id" : {
      "@type" : "alfa.rt.model.Field",
      "Name" : "id",
      "DataType" : {
        "@type" : "alfa.rt.model.OptionalDataType",
        "ComponentType" : {
          "@type" : "alfa.rt.model.ScalarDataType",
          "ScalarType" : "stringType"
        }
      },
      "SrcLocation" : {
        "@type" : "alfa.rt.model.Location",
        "path" : "/Users/sadia/IdeaProjects/smt/utils/alfadocs/test/alfa/fpml/rk/fpml-main-5-9.alfa",
        "line" : 2253
      }
    }
  },
  "LocalFieldNames" : [ "payerPartyReference", "payerAccountReference", "receiverPartyReference", "receiverAccountReference", "calculationDates", "calculationPeriods", "calculationPeriodsSchedule", "calculationPeriodsReference", "calculationPeriodsScheduleReference", "calculationPeriodsDatesReference", "commodity", "notionalQuantitySchedule", "notionalQuantity", "settlementPeriodsNotionalQuantity", "totalNotionalQuantity", "quantityReference", "calculation", "relativePaymentDates", "paymentDates", "masterAgreementPaymentDates", "flatRate", "flatRateAmount", "id" ],
  "IsSynthetic" : false
}