{
  "@type" : "alfa.rt.model.Record",
  "Doc" : "A type describing the return leg of a commodity return swap.",
  "Name" : {
    "@type" : "alfa.rt.model.UdtVersionedName",
    "FullyQualifiedName" : "FpML5.confirmation.CommodityReturnLeg",
    "UdtType" : "recordType"
  },
  "Includes" : [ ],
  "Source" : {
    "@type" : "alfa.rt.model.Union__ModelBaseNode_Source",
    "Contents" : "/#\n   A type describing the return leg of a commodity return swap.\n #/\nrecord FpML5.confirmation.CommodityReturnLeg {\n  # A reference to the party responsible for making the payments defined by this structure.\n  payerPartyReference : FpML5.confirmation.PartyReference\n\n  # A reference to the account responsible for making the payments defined by this structure.\n  payerAccountReference : FpML5.confirmation.AccountReference?\n\n  # A reference to the party that receives the payments corresponding to this structure.\n  receiverPartyReference : FpML5.confirmation.PartyReference\n\n  # A reference to the account that receives the payments corresponding to this structure.\n  receiverAccountReference : FpML5.confirmation.AccountReference?\n\n  # The Calculation Period dates for this leg of the trade where the Calculation Periods are all one day long. Only dates explicitly included determine the Calculation Periods and there is a Calculation Period for each date specified. As such one-day Calculation Period are typical a physically-settled emissions or metals trades it is expected that this element will not be used in performance swaps.\n  calculationDates : FpML5.confirmation.AdjustableDates\n\n  # The Calculation Period start dates for this leg of the swap. This type is only intended to be used if the Calculation Periods differ on each leg. If Calculation Periods mirror another leg, then the calculationPeriodsReference element should be used to point to the Calculation Periods on that leg - or the calculationPeriodsScheduleReference can be used to point to the Calculation Periods Schedule for that leg.\n  calculationPeriods : FpML5.confirmation.AdjustableDates\n\n  # The Calculation Periods for this leg of the swap. This type is only intended to be used if the Calculation Periods differ on each leg. If Calculation Periods mirror another leg, then the calculationPeriodsReference element should be used to point to the Calculation Periods on the other leg - or the calculationPeriodsScheduleReference can be used to point to the Calculation Periods Schedule for that leg.\n  calculationPeriodsSchedule : FpML5.confirmation.CommodityCalculationPeriodsSchedule\n\n  # A pointer style reference to the Calculation Periods defined on another leg.\n  calculationPeriodsReference : FpML5.confirmation.CalculationPeriodsReference\n\n  # A pointer style reference to the Calculation Periods Schedule defined on another leg.\n  calculationPeriodsScheduleReference : FpML5.confirmation.CalculationPeriodsScheduleReference\n\n  # A pointer style reference to single-day-duration Calculation Periods defined on another leg.\n  calculationPeriodsDatesReference : FpML5.confirmation.CalculationPeriodsDatesReference\n\n  # The Payment Dates of the trade relative to the Calculation Periods.\n  relativePaymentDates : FpML5.confirmation.CommodityRelativePaymentDates\n\n  # Dates on which payments will be made.\n  paymentDates : FpML5.confirmation.AdjustableDatesOrRelativeDateOffset\n\n  # If present and true indicates that the Payment Date(s) are specified in the relevant master agreement.\n  masterAgreementPaymentDates : boolean\n\n  # Describes the swap's underlyer when it has only one asset component.\n  commodity : FpML5.confirmation.Commodity\n\n  # Describes the swap's underlyer when it has multiple asset components.\n  commodityBasket : FpML5.confirmation.CommodityBasket\n\n  # Specifies the notional amount of a commodity performance type swap. It is a currency-denominated value (i.e. price-times-quantity). In confirmations is also referred to as the Notional Quantity (sic, expressed in currency units), Notional Amount, Equity Notional Amount and, in the case of reinvesting swaps, Initial Notional Amount.\n  notionalAmount : FpML5.confirmation.CommodityNotionalAmount\n\n  # A reference to the Return swap notional amount defined in another leg of the return swap.\n  notionalAmountReference : FpML5.confirmation.CommodityNotionalAmountReference\n\n  # Specifies, in relation to each Payment Date, the return percentage which, when multiplied times the notional amount is the amount to which the Payment Date relates.\n  commodityReturnCalculation : FpML5.confirmation.CommodityReturnCalculation\n\n  id : string?\n\n}"
  },
  "AllFields" : {
    "payerPartyReference" : {
      "@type" : "alfa.rt.model.Field",
      "Doc" : "A reference to the party responsible for making the payments defined by this structure.",
      "Name" : "payerPartyReference",
      "DataType" : {
        "@type" : "alfa.rt.model.UdtDataType",
        "FullyQualifiedName" : "FpML5.confirmation.PartyReference",
        "UdtType" : "recordType"
      },
      "DeclTypeDefDataType" : {
        "@type" : "alfa.rt.model.TypeDefDataType",
        "TypeName" : "FpML5.confirmation.PartyReference",
        "FinalType" : {
          "@type" : "alfa.rt.model.UdtDataType",
          "FullyQualifiedName" : "FpML5.confirmation.PartyReference",
          "UdtType" : "recordType"
        }
      },
      "SrcLocation" : {
        "@type" : "alfa.rt.model.Location",
        "path" : "/Users/sadia/IdeaProjects/smt/utils/alfadocs/test/alfa/fpml/conf/fpml-main-5-9.alfa",
        "line" : 20650
      }
    },
    "payerAccountReference" : {
      "@type" : "alfa.rt.model.Field",
      "Doc" : "A reference to the account responsible for making the payments defined by this structure.",
      "Name" : "payerAccountReference",
      "DataType" : {
        "@type" : "alfa.rt.model.OptionalDataType",
        "ComponentType" : {
          "@type" : "alfa.rt.model.UdtDataType",
          "FullyQualifiedName" : "FpML5.confirmation.AccountReference",
          "UdtType" : "recordType"
        }
      },
      "SrcLocation" : {
        "@type" : "alfa.rt.model.Location",
        "path" : "/Users/sadia/IdeaProjects/smt/utils/alfadocs/test/alfa/fpml/conf/fpml-main-5-9.alfa",
        "line" : 20653
      }
    },
    "receiverPartyReference" : {
      "@type" : "alfa.rt.model.Field",
      "Doc" : "A reference to the party that receives the payments corresponding to this structure.",
      "Name" : "receiverPartyReference",
      "DataType" : {
        "@type" : "alfa.rt.model.UdtDataType",
        "FullyQualifiedName" : "FpML5.confirmation.PartyReference",
        "UdtType" : "recordType"
      },
      "DeclTypeDefDataType" : {
        "@type" : "alfa.rt.model.TypeDefDataType",
        "TypeName" : "FpML5.confirmation.PartyReference",
        "FinalType" : {
          "@type" : "alfa.rt.model.UdtDataType",
          "FullyQualifiedName" : "FpML5.confirmation.PartyReference",
          "UdtType" : "recordType"
        }
      },
      "SrcLocation" : {
        "@type" : "alfa.rt.model.Location",
        "path" : "/Users/sadia/IdeaProjects/smt/utils/alfadocs/test/alfa/fpml/conf/fpml-main-5-9.alfa",
        "line" : 20656
      }
    },
    "receiverAccountReference" : {
      "@type" : "alfa.rt.model.Field",
      "Doc" : "A reference to the account that receives the payments corresponding to this structure.",
      "Name" : "receiverAccountReference",
      "DataType" : {
        "@type" : "alfa.rt.model.OptionalDataType",
        "ComponentType" : {
          "@type" : "alfa.rt.model.UdtDataType",
          "FullyQualifiedName" : "FpML5.confirmation.AccountReference",
          "UdtType" : "recordType"
        }
      },
      "SrcLocation" : {
        "@type" : "alfa.rt.model.Location",
        "path" : "/Users/sadia/IdeaProjects/smt/utils/alfadocs/test/alfa/fpml/conf/fpml-main-5-9.alfa",
        "line" : 20659
      }
    },
    "calculationDates" : {
      "@type" : "alfa.rt.model.Field",
      "Doc" : "The Calculation Period dates for this leg of the trade where the Calculation Periods are all one day long. Only dates explicitly included determine the Calculation Periods and there is a Calculation Period for each date specified. As such one-day Calculation Period are typical a physically-settled emissions or metals trades it is expected that this element will not be used in performance swaps.",
      "Name" : "calculationDates",
      "DataType" : {
        "@type" : "alfa.rt.model.UdtDataType",
        "FullyQualifiedName" : "FpML5.confirmation.AdjustableDates",
        "UdtType" : "recordType"
      },
      "DeclTypeDefDataType" : {
        "@type" : "alfa.rt.model.TypeDefDataType",
        "TypeName" : "FpML5.confirmation.AdjustableDates",
        "FinalType" : {
          "@type" : "alfa.rt.model.UdtDataType",
          "FullyQualifiedName" : "FpML5.confirmation.AdjustableDates",
          "UdtType" : "recordType"
        }
      },
      "SrcLocation" : {
        "@type" : "alfa.rt.model.Location",
        "path" : "/Users/sadia/IdeaProjects/smt/utils/alfadocs/test/alfa/fpml/conf/fpml-main-5-9.alfa",
        "line" : 20662
      }
    },
    "calculationPeriods" : {
      "@type" : "alfa.rt.model.Field",
      "Doc" : "The Calculation Period start dates for this leg of the swap. This type is only intended to be used if the Calculation Periods differ on each leg. If Calculation Periods mirror another leg, then the calculationPeriodsReference element should be used to point to the Calculation Periods on that leg - or the calculationPeriodsScheduleReference can be used to point to the Calculation Periods Schedule for that leg.",
      "Name" : "calculationPeriods",
      "DataType" : {
        "@type" : "alfa.rt.model.UdtDataType",
        "FullyQualifiedName" : "FpML5.confirmation.AdjustableDates",
        "UdtType" : "recordType"
      },
      "DeclTypeDefDataType" : {
        "@type" : "alfa.rt.model.TypeDefDataType",
        "TypeName" : "FpML5.confirmation.AdjustableDates",
        "FinalType" : {
          "@type" : "alfa.rt.model.UdtDataType",
          "FullyQualifiedName" : "FpML5.confirmation.AdjustableDates",
          "UdtType" : "recordType"
        }
      },
      "SrcLocation" : {
        "@type" : "alfa.rt.model.Location",
        "path" : "/Users/sadia/IdeaProjects/smt/utils/alfadocs/test/alfa/fpml/conf/fpml-main-5-9.alfa",
        "line" : 20665
      }
    },
    "calculationPeriodsSchedule" : {
      "@type" : "alfa.rt.model.Field",
      "Doc" : "The Calculation Periods for this leg of the swap. This type is only intended to be used if the Calculation Periods differ on each leg. If Calculation Periods mirror another leg, then the calculationPeriodsReference element should be used to point to the Calculation Periods on the other leg - or the calculationPeriodsScheduleReference can be used to point to the Calculation Periods Schedule for that leg.",
      "Name" : "calculationPeriodsSchedule",
      "DataType" : {
        "@type" : "alfa.rt.model.UdtDataType",
        "FullyQualifiedName" : "FpML5.confirmation.CommodityCalculationPeriodsSchedule",
        "UdtType" : "recordType"
      },
      "DeclTypeDefDataType" : {
        "@type" : "alfa.rt.model.TypeDefDataType",
        "TypeName" : "FpML5.confirmation.CommodityCalculationPeriodsSchedule",
        "FinalType" : {
          "@type" : "alfa.rt.model.UdtDataType",
          "FullyQualifiedName" : "FpML5.confirmation.CommodityCalculationPeriodsSchedule",
          "UdtType" : "recordType"
        }
      },
      "SrcLocation" : {
        "@type" : "alfa.rt.model.Location",
        "path" : "/Users/sadia/IdeaProjects/smt/utils/alfadocs/test/alfa/fpml/conf/fpml-main-5-9.alfa",
        "line" : 20668
      }
    },
    "calculationPeriodsReference" : {
      "@type" : "alfa.rt.model.Field",
      "Doc" : "A pointer style reference to the Calculation Periods defined on another leg.",
      "Name" : "calculationPeriodsReference",
      "DataType" : {
        "@type" : "alfa.rt.model.UdtDataType",
        "FullyQualifiedName" : "FpML5.confirmation.CalculationPeriodsReference",
        "UdtType" : "recordType"
      },
      "DeclTypeDefDataType" : {
        "@type" : "alfa.rt.model.TypeDefDataType",
        "TypeName" : "FpML5.confirmation.CalculationPeriodsReference",
        "FinalType" : {
          "@type" : "alfa.rt.model.UdtDataType",
          "FullyQualifiedName" : "FpML5.confirmation.CalculationPeriodsReference",
          "UdtType" : "recordType"
        }
      },
      "SrcLocation" : {
        "@type" : "alfa.rt.model.Location",
        "path" : "/Users/sadia/IdeaProjects/smt/utils/alfadocs/test/alfa/fpml/conf/fpml-main-5-9.alfa",
        "line" : 20671
      }
    },
    "calculationPeriodsScheduleReference" : {
      "@type" : "alfa.rt.model.Field",
      "Doc" : "A pointer style reference to the Calculation Periods Schedule defined on another leg.",
      "Name" : "calculationPeriodsScheduleReference",
      "DataType" : {
        "@type" : "alfa.rt.model.UdtDataType",
        "FullyQualifiedName" : "FpML5.confirmation.CalculationPeriodsScheduleReference",
        "UdtType" : "recordType"
      },
      "DeclTypeDefDataType" : {
        "@type" : "alfa.rt.model.TypeDefDataType",
        "TypeName" : "FpML5.confirmation.CalculationPeriodsScheduleReference",
        "FinalType" : {
          "@type" : "alfa.rt.model.UdtDataType",
          "FullyQualifiedName" : "FpML5.confirmation.CalculationPeriodsScheduleReference",
          "UdtType" : "recordType"
        }
      },
      "SrcLocation" : {
        "@type" : "alfa.rt.model.Location",
        "path" : "/Users/sadia/IdeaProjects/smt/utils/alfadocs/test/alfa/fpml/conf/fpml-main-5-9.alfa",
        "line" : 20674
      }
    },
    "calculationPeriodsDatesReference" : {
      "@type" : "alfa.rt.model.Field",
      "Doc" : "A pointer style reference to single-day-duration Calculation Periods defined on another leg.",
      "Name" : "calculationPeriodsDatesReference",
      "DataType" : {
        "@type" : "alfa.rt.model.UdtDataType",
        "FullyQualifiedName" : "FpML5.confirmation.CalculationPeriodsDatesReference",
        "UdtType" : "recordType"
      },
      "DeclTypeDefDataType" : {
        "@type" : "alfa.rt.model.TypeDefDataType",
        "TypeName" : "FpML5.confirmation.CalculationPeriodsDatesReference",
        "FinalType" : {
          "@type" : "alfa.rt.model.UdtDataType",
          "FullyQualifiedName" : "FpML5.confirmation.CalculationPeriodsDatesReference",
          "UdtType" : "recordType"
        }
      },
      "SrcLocation" : {
        "@type" : "alfa.rt.model.Location",
        "path" : "/Users/sadia/IdeaProjects/smt/utils/alfadocs/test/alfa/fpml/conf/fpml-main-5-9.alfa",
        "line" : 20677
      }
    },
    "relativePaymentDates" : {
      "@type" : "alfa.rt.model.Field",
      "Doc" : "The Payment Dates of the trade relative to the Calculation Periods.",
      "Name" : "relativePaymentDates",
      "DataType" : {
        "@type" : "alfa.rt.model.UdtDataType",
        "FullyQualifiedName" : "FpML5.confirmation.CommodityRelativePaymentDates",
        "UdtType" : "recordType"
      },
      "DeclTypeDefDataType" : {
        "@type" : "alfa.rt.model.TypeDefDataType",
        "TypeName" : "FpML5.confirmation.CommodityRelativePaymentDates",
        "FinalType" : {
          "@type" : "alfa.rt.model.UdtDataType",
          "FullyQualifiedName" : "FpML5.confirmation.CommodityRelativePaymentDates",
          "UdtType" : "recordType"
        }
      },
      "SrcLocation" : {
        "@type" : "alfa.rt.model.Location",
        "path" : "/Users/sadia/IdeaProjects/smt/utils/alfadocs/test/alfa/fpml/conf/fpml-main-5-9.alfa",
        "line" : 20680
      }
    },
    "paymentDates" : {
      "@type" : "alfa.rt.model.Field",
      "Doc" : "Dates on which payments will be made.",
      "Name" : "paymentDates",
      "DataType" : {
        "@type" : "alfa.rt.model.UdtDataType",
        "FullyQualifiedName" : "FpML5.confirmation.AdjustableDatesOrRelativeDateOffset",
        "UdtType" : "recordType"
      },
      "DeclTypeDefDataType" : {
        "@type" : "alfa.rt.model.TypeDefDataType",
        "TypeName" : "FpML5.confirmation.AdjustableDatesOrRelativeDateOffset",
        "FinalType" : {
          "@type" : "alfa.rt.model.UdtDataType",
          "FullyQualifiedName" : "FpML5.confirmation.AdjustableDatesOrRelativeDateOffset",
          "UdtType" : "recordType"
        }
      },
      "SrcLocation" : {
        "@type" : "alfa.rt.model.Location",
        "path" : "/Users/sadia/IdeaProjects/smt/utils/alfadocs/test/alfa/fpml/conf/fpml-main-5-9.alfa",
        "line" : 20683
      }
    },
    "masterAgreementPaymentDates" : {
      "@type" : "alfa.rt.model.Field",
      "Doc" : "If present and true indicates that the Payment Date(s) are specified in the relevant master agreement.",
      "Name" : "masterAgreementPaymentDates",
      "DataType" : {
        "@type" : "alfa.rt.model.ScalarDataType",
        "ScalarType" : "booleanType"
      },
      "SrcLocation" : {
        "@type" : "alfa.rt.model.Location",
        "path" : "/Users/sadia/IdeaProjects/smt/utils/alfadocs/test/alfa/fpml/conf/fpml-main-5-9.alfa",
        "line" : 20686
      }
    },
    "commodity" : {
      "@type" : "alfa.rt.model.Field",
      "Doc" : "Describes the swap's underlyer when it has only one asset component.",
      "Name" : "commodity",
      "DataType" : {
        "@type" : "alfa.rt.model.UdtDataType",
        "FullyQualifiedName" : "FpML5.confirmation.Commodity",
        "UdtType" : "recordType"
      },
      "DeclTypeDefDataType" : {
        "@type" : "alfa.rt.model.TypeDefDataType",
        "TypeName" : "FpML5.confirmation.Commodity",
        "FinalType" : {
          "@type" : "alfa.rt.model.UdtDataType",
          "FullyQualifiedName" : "FpML5.confirmation.Commodity",
          "UdtType" : "recordType"
        }
      },
      "SrcLocation" : {
        "@type" : "alfa.rt.model.Location",
        "path" : "/Users/sadia/IdeaProjects/smt/utils/alfadocs/test/alfa/fpml/conf/fpml-main-5-9.alfa",
        "line" : 20689
      }
    },
    "commodityBasket" : {
      "@type" : "alfa.rt.model.Field",
      "Doc" : "Describes the swap's underlyer when it has multiple asset components.",
      "Name" : "commodityBasket",
      "DataType" : {
        "@type" : "alfa.rt.model.UdtDataType",
        "FullyQualifiedName" : "FpML5.confirmation.CommodityBasket",
        "UdtType" : "recordType"
      },
      "DeclTypeDefDataType" : {
        "@type" : "alfa.rt.model.TypeDefDataType",
        "TypeName" : "FpML5.confirmation.CommodityBasket",
        "FinalType" : {
          "@type" : "alfa.rt.model.UdtDataType",
          "FullyQualifiedName" : "FpML5.confirmation.CommodityBasket",
          "UdtType" : "recordType"
        }
      },
      "SrcLocation" : {
        "@type" : "alfa.rt.model.Location",
        "path" : "/Users/sadia/IdeaProjects/smt/utils/alfadocs/test/alfa/fpml/conf/fpml-main-5-9.alfa",
        "line" : 20692
      }
    },
    "notionalAmount" : {
      "@type" : "alfa.rt.model.Field",
      "Doc" : "Specifies the notional amount of a commodity performance type swap. It is a currency-denominated value (i.e. price-times-quantity). In confirmations is also referred to as the Notional Quantity (sic, expressed in currency units), Notional Amount, Equity Notional Amount and, in the case of reinvesting swaps, Initial Notional Amount.",
      "Name" : "notionalAmount",
      "DataType" : {
        "@type" : "alfa.rt.model.UdtDataType",
        "FullyQualifiedName" : "FpML5.confirmation.CommodityNotionalAmount",
        "UdtType" : "recordType"
      },
      "DeclTypeDefDataType" : {
        "@type" : "alfa.rt.model.TypeDefDataType",
        "TypeName" : "FpML5.confirmation.CommodityNotionalAmount",
        "FinalType" : {
          "@type" : "alfa.rt.model.UdtDataType",
          "FullyQualifiedName" : "FpML5.confirmation.CommodityNotionalAmount",
          "UdtType" : "recordType"
        }
      },
      "SrcLocation" : {
        "@type" : "alfa.rt.model.Location",
        "path" : "/Users/sadia/IdeaProjects/smt/utils/alfadocs/test/alfa/fpml/conf/fpml-main-5-9.alfa",
        "line" : 20695
      }
    },
    "notionalAmountReference" : {
      "@type" : "alfa.rt.model.Field",
      "Doc" : "A reference to the Return swap notional amount defined in another leg of the return swap.",
      "Name" : "notionalAmountReference",
      "DataType" : {
        "@type" : "alfa.rt.model.UdtDataType",
        "FullyQualifiedName" : "FpML5.confirmation.CommodityNotionalAmountReference",
        "UdtType" : "recordType"
      },
      "DeclTypeDefDataType" : {
        "@type" : "alfa.rt.model.TypeDefDataType",
        "TypeName" : "FpML5.confirmation.CommodityNotionalAmountReference",
        "FinalType" : {
          "@type" : "alfa.rt.model.UdtDataType",
          "FullyQualifiedName" : "FpML5.confirmation.CommodityNotionalAmountReference",
          "UdtType" : "recordType"
        }
      },
      "SrcLocation" : {
        "@type" : "alfa.rt.model.Location",
        "path" : "/Users/sadia/IdeaProjects/smt/utils/alfadocs/test/alfa/fpml/conf/fpml-main-5-9.alfa",
        "line" : 20698
      }
    },
    "commodityReturnCalculation" : {
      "@type" : "alfa.rt.model.Field",
      "Doc" : "Specifies, in relation to each Payment Date, the return percentage which, when multiplied times the notional amount is the amount to which the Payment Date relates.",
      "Name" : "commodityReturnCalculation",
      "DataType" : {
        "@type" : "alfa.rt.model.UdtDataType",
        "FullyQualifiedName" : "FpML5.confirmation.CommodityReturnCalculation",
        "UdtType" : "recordType"
      },
      "DeclTypeDefDataType" : {
        "@type" : "alfa.rt.model.TypeDefDataType",
        "TypeName" : "FpML5.confirmation.CommodityReturnCalculation",
        "FinalType" : {
          "@type" : "alfa.rt.model.UdtDataType",
          "FullyQualifiedName" : "FpML5.confirmation.CommodityReturnCalculation",
          "UdtType" : "recordType"
        }
      },
      "SrcLocation" : {
        "@type" : "alfa.rt.model.Location",
        "path" : "/Users/sadia/IdeaProjects/smt/utils/alfadocs/test/alfa/fpml/conf/fpml-main-5-9.alfa",
        "line" : 20701
      }
    },
    "id" : {
      "@type" : "alfa.rt.model.Field",
      "Name" : "id",
      "DataType" : {
        "@type" : "alfa.rt.model.OptionalDataType",
        "ComponentType" : {
          "@type" : "alfa.rt.model.ScalarDataType",
          "ScalarType" : "stringType"
        }
      },
      "SrcLocation" : {
        "@type" : "alfa.rt.model.Location",
        "path" : "/Users/sadia/IdeaProjects/smt/utils/alfadocs/test/alfa/fpml/conf/fpml-main-5-9.alfa",
        "line" : 20704
      }
    }
  },
  "LocalFieldNames" : [ "payerPartyReference", "payerAccountReference", "receiverPartyReference", "receiverAccountReference", "calculationDates", "calculationPeriods", "calculationPeriodsSchedule", "calculationPeriodsReference", "calculationPeriodsScheduleReference", "calculationPeriodsDatesReference", "relativePaymentDates", "paymentDates", "masterAgreementPaymentDates", "commodity", "commodityBasket", "notionalAmount", "notionalAmountReference", "commodityReturnCalculation", "id" ],
  "IsSynthetic" : false
}